chimera/__init__.py
chimera/_version.py
chimera/chimera.py
matter_chimera-1.0.dist-info/LICENSE
matter_chimera-1.0.dist-info/METADATA
matter_chimera-1.0.dist-info/WHEEL
matter_chimera-1.0.dist-info/top_level.txt
matter_chimera-1.0.dist-info/RECORD
