Metadata-Version: 2.1
Name: matter-chimera
Version: 1.0
Summary: UNKNOWN
Home-page: https://github.com/aspuru-guzik-group/chimera
Author: Florian Häse, Matteo Aldeghi
Author-email: matteo.aldeghi@vectorinstitute.ai
License: MIT
Platform: UNKNOWN
Classifier: Programming Language :: Python
Classifier: Intended Audience :: Science/Research
Classifier: Topic :: Scientific/Engineering
Requires-Python: >=3
Requires-Dist: numpy
